hash_ring.py
setup.py
hash_ring.egg-info/PKG-INFO
hash_ring.egg-info/SOURCES.txt
hash_ring.egg-info/dependency_links.txt
hash_ring.egg-info/top_level.txt