Metadata-Version: 1.0
Name: hash-ring
Version: 1.0
Summary: Implements consistent hashing in Python (using md5 as hashing function).
Home-page: http://www.amix.dk/
Author: Amir Salihefendic
Author-email: amix@amix.dk
License: BSD
Keywords: memcached hashing hash consistent
Platform: Any
Classifier: Development Status :: 4 - Beta
Classifier: Intended Audience :: Developers
Classifier: License :: OSI Approved :: BSD License
Classifier: Operating System :: OS Independent
Classifier: Programming Language :: Python
Classifier: Topic :: Software Development :: Libraries :: Python Modules
